{
  "CountryEmojis": {
    "version": "1.0.0",
    "type": "helper",
    "lastUpdated": "2025-11-01T16:38:36.543Z",
    "hash": "-44506a3b"
  },
  "Shopping list": {
    "version": "1.0.0",
    "type": "widget",
    "lastUpdated": "2025-11-01T15:34:03.322Z",
    "hash": "51dbd10b"
  },
  "Pull": {
    "version": "1.0.0",
    "type": "script",
    "lastUpdated": "2025-11-01T15:34:03.322Z",
    "hash": "-6779ab7b"
  },
  "Countries a year": {
    "version": "1.0.2",
    "type": "widget",
    "lastUpdated": "2025-11-01T16:49:52.178Z",
    "hash": "-72bcdea"
  },
  "Servers healthz": {
    "version": "1.1.0",
    "type": "widget",
    "lastUpdated": "2025-11-01T16:31:49.415Z",
    "hash": "25ab8f47"
  },
  "Push": {
    "version": "1.1.4",
    "type": "script",
    "lastUpdated": "2025-11-01T16:49:08.460Z",
    "hash": "8512c51"
  },
  "SetWidgetBackground": {
    "version": "1.0.0",
    "type": "helper",
    "lastUpdated": "2025-11-01T16:38:36.543Z",
    "hash": "-138842ba"
  },
  "Git": {
    "hash": "-4106cb31",
    "lastUpdated": "2025-11-01T16:38:36.543Z"
  }
}
